altair_grid/__init__.py
altair_grid-0.0.3.dist-info/LICENSE
altair_grid-0.0.3.dist-info/METADATA
altair_grid-0.0.3.dist-info/WHEEL
altair_grid-0.0.3.dist-info/top_level.txt
altair_grid-0.0.3.dist-info/RECORD
