Metadata-Version: 2.1
Name: altair-grid
Version: 0.0.3
Summary: A Grid.news theme for Python's Altair statistical visualization library
Home-page: http://www.github.com/gridviz/altair-grid
Author: Grid Investigations and Data
Author-email: mstiles@grid.news
License: MIT
Platform: UNKNOWN
Classifier: Development Status :: 5 - Production/Stable
Classifier: Programming Language :: Python
Classifier: Programming Language :: Python :: 2
Classifier: Programming Language :: Python :: 2.7
Classifier: Programming Language :: Python :: 3
Classifier: Programming Language :: Python :: 3.6
Classifier: Programming Language :: Python :: 3.7
Classifier: Programming Language :: Python :: 3.8
Classifier: Programming Language :: Python :: 3.9
Classifier: License :: OSI Approved :: MIT License
License-File: LICENSE
